vyattaconfparser/__init__.py
vyattaconfparser/parser.py
VyattaConfParser-0.5.5.dist-info/AUTHORS
VyattaConfParser-0.5.5.dist-info/LICENSE
VyattaConfParser-0.5.5.dist-info/METADATA
VyattaConfParser-0.5.5.dist-info/WHEEL
VyattaConfParser-0.5.5.dist-info/top_level.txt
VyattaConfParser-0.5.5.dist-info/RECORD
