Metadata-Version: 2.1
Name: VyattaConfParser
Version: 0.5.5
Summary: A python config parser for Vyatta
Home-page: https://github.com/hedin/vyatta-conf-parser
Author: Aleksandr Mironov
Author-email: a.m.mironov@gmail.com
License: UNKNOWN
Platform: UNKNOWN
Classifier: Programming Language :: Python :: 2
Classifier: Programming Language :: Python :: 2.7
Classifier: Programming Language :: Python :: 3
Classifier: Programming Language :: Python :: 3.3
Classifier: Programming Language :: Python :: 3.4
Classifier: Programming Language :: Python :: 3.5
Classifier: License :: OSI Approved :: MIT License
Classifier: Operating System :: OS Independent
Classifier: Intended Audience :: Developers
Classifier: Topic :: Software Development :: Libraries :: Python Modules
Classifier: Development Status :: 4 - Beta
Provides-Extra: dev
Requires-Dist: datadiff ; extra == 'dev'
